trio_paho_mqtt/__init__.py
trio_paho_mqtt/trio_paho_mqtt.py
trio_paho_mqtt-0.3.1.dist-info/LICENSE
trio_paho_mqtt-0.3.1.dist-info/METADATA
trio_paho_mqtt-0.3.1.dist-info/WHEEL
trio_paho_mqtt-0.3.1.dist-info/top_level.txt
trio_paho_mqtt-0.3.1.dist-info/RECORD
