Metadata-Version: 2.1
Name: trio-paho-mqtt
Version: 0.3.1
Summary: trio async MQTT Client
Home-page: https://github.com/bkanuka/trio-paho-mqtt
Author-email: bkanuka@gmail.com
License: UNKNOWN
Download-URL: https://github.com/bkanuka/trio-paho-mqtt/archive/v0.3.1.tar.gz
Project-URL: Source, https://github.com/bkanuka/trio-paho-mqtt
Keywords: trio mqtt
Platform: UNKNOWN
Classifier: Development Status :: 4 - Beta
Classifier: Framework :: Trio
Classifier: Topic :: Software Development :: Libraries :: Python Modules
Classifier: Intended Audience :: Developers
Classifier: License :: OSI Approved :: Apache Software License
Classifier: Programming Language :: Python :: 3.5
Classifier: Programming Language :: Python :: 3.6
Classifier: Programming Language :: Python :: 3.7
Classifier: Programming Language :: Python :: 3.8
Requires-Python: >=3.5, <4
Requires-Dist: paho-mqtt
Requires-Dist: trio
